AUTHORS
CONTRIBUTING.md
LICENSE
MANIFEST.in
README.md
config.py
fabfile.py
requirements.base.txt
requirements.couchbase.txt
requirements.dev.txt
requirements.txt
runtime.txt
setup.cfg
setup.py
start_dev_will.py
will/__init__.py
will/acl.py
will/decorators.py
will/listener.py
will/main.py
will/plugin.py
will/scheduler.py
will/settings.py
will/utils.py
will.egg-info/PKG-INFO
will.egg-info/SOURCES.txt
will.egg-info/dependency_links.txt
will.egg-info/entry_points.txt
will.egg-info/requires.txt
will.egg-info/top_level.txt
will/mixins/__init__.py
will/mixins/email.py
will/mixins/errors.py
will/mixins/hipchat.py
will/mixins/naturaltime.py
will/mixins/plugins_library.py
will/mixins/room.py
will/mixins/roster.py
will/mixins/schedule.py
will/mixins/settings.py
will/mixins/storage.py
will/plugins/__init__.py
will/plugins/admin/__init__.py
will/plugins/admin/keep_alive.py
will/plugins/admin/ping.py
will/plugins/admin/say.py
will/plugins/admin/storage.py
will/plugins/admin/version.py
will/plugins/chat_room/__init__.py
will/plugins/chat_room/rooms.py
will/plugins/chat_room/roster.py
will/plugins/chat_room/set_topic.py
will/plugins/devops/__init__.py
will/plugins/devops/bitbucket_is_up.py
will/plugins/devops/emergency_contacts.py
will/plugins/devops/github_is_up.py
will/plugins/devops/heroku_is_up.py
will/plugins/devops/hipchat_is_up.py
will/plugins/devops/pagerduty.py
will/plugins/friendly/__init__.py
will/plugins/friendly/cookies.py
will/plugins/friendly/hello.py
will/plugins/friendly/love.py
will/plugins/friendly/mornin.py
will/plugins/friendly/random_topic.py
will/plugins/friendly/talk_back.py
will/plugins/friendly/thanks.py
will/plugins/fun/__init__.py
will/plugins/fun/definition.py
will/plugins/fun/googlepoem.py
will/plugins/fun/pug.py
will/plugins/help/__init__.py
will/plugins/help/help.py
will/plugins/help/programmer_help.py
will/plugins/productivity/__init__.py
will/plugins/productivity/bitly.py
will/plugins/productivity/hangout.py
will/plugins/productivity/images.py
will/plugins/productivity/remind.py
will/plugins/productivity/world_time.py
will/plugins/web/__init__.py
will/plugins/web/home.py
will/scripts/__init__.py
