Metadata-Version: 1.1
Name: will
Version: 1.0.1
Summary: A friendly python hipchat bot
Home-page: https://github.com/skoczen/will
Author: Steven Skoczen
Author-email: skoczen@gmail.com
License: UNKNOWN
Download-URL: ['https://github.com/skoczen/will/tarball/1.0.1']
Keywords: hipchat,bot,ai
Platform: UNKNOWN
Classifier: Programming Language :: Python
Classifier: License :: OSI Approved :: BSD License
Classifier: Operating System :: OS Independent
Classifier: Development Status :: 4 - Beta
Classifier: Environment :: Web Environment
Classifier: Intended Audience :: Developers
Classifier: Topic :: Internet :: WWW/HTTP
Classifier: Topic :: Communications :: Chat
Classifier: Topic :: Software Development :: Libraries :: Python Modules
